diff_search-0.0.0.dist-info/licenses/LICENSE
diffsearch/__init__.py
diffsearch/version.py
diff_search-0.0.0.dist-info/METADATA
diff_search-0.0.0.dist-info/WHEEL
diff_search-0.0.0.dist-info/entry_points.txt
diff_search-0.0.0.dist-info/top_level.txt
diff_search-0.0.0.dist-info/RECORD
